prismnlq/__init__.py
prismnlq/auth.py
prismnlq/nlq.py
prismnlq/utils.py
prismnlq-0.1.6.dist-info/METADATA
prismnlq-0.1.6.dist-info/WHEEL
prismnlq-0.1.6.dist-info/top_level.txt
prismnlq-0.1.6.dist-info/RECORD
