Metadata-Version: 2.4
Name: prismnlq
Version: 0.1.6
Summary: PrismNLQ
Author: Prism39 Inc.
Author-email: info@prism39.com
License: PrismStudio End User License Agreement
Classifier: Programming Language :: Python :: 3
Classifier: Programming Language :: Python :: 3.12
Requires-Dist: aiohttp
Requires-Dist: sseclient
Requires-Dist: pandas
Requires-Dist: polars
Requires-Dist: pyarrow
Requires-Dist: tqdm
Requires-Dist: requests
Dynamic: author
Dynamic: author-email
Dynamic: classifier
Dynamic: license
Dynamic: requires-dist
Dynamic: summary
